ml4teens/__init__.py
ml4teens/version.py
ml4teens/blocks/__init__.py
ml4teens/blocks/display.py
ml4teens/blocks/drain.py
ml4teens/blocks/forEach.py
ml4teens/blocks/ifElse.py
ml4teens/blocks/terminal.py
ml4teens/blocks/timer.py
ml4teens/blocks/value.py
ml4teens/blocks/values.py
ml4teens/blocks/ds/__init__.py
ml4teens/blocks/ds/clustering.py
ml4teens/blocks/ds/confusionMatrix.py
ml4teens/blocks/ds/dataLabelizer.py
ml4teens/blocks/ds/dataWarehouse.py
ml4teens/blocks/ds/plot2D.py
ml4teens/blocks/ds/plot3D.py
ml4teens/blocks/ds/splitColumns.py
ml4teens/blocks/img/__init__.py
ml4teens/blocks/img/convertImage.py
ml4teens/blocks/img/depthEstimation.py
ml4teens/blocks/img/distance.py
ml4teens/blocks/img/embedding.py
ml4teens/blocks/img/faceBoxing.py
ml4teens/blocks/img/faceLandmarks.py
ml4teens/blocks/img/faceRecognition.py
ml4teens/blocks/img/handFeatures.py
ml4teens/blocks/img/handGestures.py
ml4teens/blocks/img/handLandmarks.py
ml4teens/blocks/img/histogram.py
ml4teens/blocks/img/imageOp.py
ml4teens/blocks/img/imageSource.py
ml4teens/blocks/img/imageToText.py
ml4teens/blocks/img/mergeChannels.py
ml4teens/blocks/img/objectCLS.py
ml4teens/blocks/img/objectID.py
ml4teens/blocks/img/poseEstimation.py
ml4teens/blocks/img/resizeImage.py
ml4teens/blocks/img/segmentAll.py
ml4teens/blocks/img/segmentation.py
ml4teens/blocks/img/similarity.py
ml4teens/blocks/img/singleChannel.py
ml4teens/blocks/img/splitChannels.py
ml4teens/blocks/img/threshold.py
ml4teens/blocks/img/trimImage.py
ml4teens/blocks/img/video2file.py
ml4teens/blocks/img/videoSource.py
ml4teens/blocks/img/yoloPredict.py
ml4teens/blocks/img/yoloTrain.py
ml4teens/blocks/nlp/__init__.py
ml4teens/blocks/nlp/audioPlayer.py
ml4teens/blocks/nlp/audioSource.py
ml4teens/blocks/nlp/inputText.py
ml4teens/blocks/nlp/openai.py
ml4teens/blocks/nlp/similarity.py
ml4teens/blocks/nlp/tfidf.py
ml4teens/blocks/nlp/transcribe.py
ml4teens/core/__init__.py
ml4teens/core/block.py
ml4teens/core/context.py
ml4teens/core/signalType.py
ml4teens-0.1.46.dist-info/LICENSE
ml4teens-0.1.46.dist-info/METADATA
ml4teens-0.1.46.dist-info/WHEEL
ml4teens-0.1.46.dist-info/top_level.txt
ml4teens-0.1.46.dist-info/RECORD
