Metadata-Version: 2.1
Name: ml4teens
Version: 0.1.46
Summary: Machine Learning para Adolescentes (Machine Learning for Teens)
Home-page: https://github.com/FranPuentes/ML4Teens
Author: Francisco Puentes
Author-email: fran@puentescalvo.com
License-File: LICENSE
Requires-Dist: Pillow
Requires-Dist: PyYAML
Requires-Dist: accelerate
Requires-Dist: cohere
Requires-Dist: ffmpeg
Requires-Dist: gradio
Requires-Dist: imageio
Requires-Dist: ipycanvas (==0.11)
Requires-Dist: ipyevents
Requires-Dist: ipython
Requires-Dist: ipywidgets (==7.7.1)
Requires-Dist: jupyter-ui-poll
Requires-Dist: keras
Requires-Dist: librosa
Requires-Dist: matplotlib (>=3.0)
Requires-Dist: mediapipe (>=0.10.9)
Requires-Dist: nsnet2-denoiser
Requires-Dist: numpy
Requires-Dist: openai
Requires-Dist: opencv-python (>=4.9)
Requires-Dist: pandas (>=1.3.4)
Requires-Dist: plotly
Requires-Dist: pyaudio
Requires-Dist: requests
Requires-Dist: scikit-image
Requires-Dist: scipy (==1.12.0)
Requires-Dist: seaborn
Requires-Dist: sounddevice
Requires-Dist: tiktoken
Requires-Dist: torch (==2.2.2)
Requires-Dist: torchaudio
Requires-Dist: transformers
Requires-Dist: ultralytics
